asyncsms/__init__.py
asyncsms/asyncsms.py
AsyncSMS-0.1.dist-info/LICENSE
AsyncSMS-0.1.dist-info/METADATA
AsyncSMS-0.1.dist-info/WHEEL
AsyncSMS-0.1.dist-info/top_level.txt
AsyncSMS-0.1.dist-info/RECORD
