Metadata-Version: 2.1
Name: AsyncSMS
Version: 0.1
Summary: sms-activate 异步版。
Home-page: https://github.com/songjian/async-sms
Author: sj
Author-email: boss@codeorder.cn
License: UNKNOWN
Platform: UNKNOWN
Classifier: Programming Language :: Python :: 3
Classifier: License :: OSI Approved :: MIT License
Classifier: Operating System :: OS Independent
License-File: LICENSE
Requires-Dist: smsactivate (>=1.5)
Requires-Dist: requests (>=2.28.1)
